{
  "type": "minecraft:stonecutting",
  "ingredient": [
    {
      "item": "minecraft:warped_stem"
    },
    {
      "item": "minecraft:stripped_warped_stem"
    },
    {
      "item": "minecraft:warped_hyphae"
    },
    {
      "item": "minecraft:stripped_warped_hyphae"
    }
  ],
  "result": {
    "id": "stylishstiles:warped_stile",
    "count": 4
  },
  "fabric:load_conditions": [
    {
      "values": [
        "stylishstiles"
      ],
      "condition": "fabric:all_mods_loaded"
    }
  ]
}
