{
  "criteria": {
    "requirement": {
      "trigger": "minecraft:inventory_changed",
      "conditions": {
        "items": [
          {
            "items": [
              "biomesoplenty:maple_stairs"
            ]
          }
        ]
      }
    }
  },
  "rewards": {
    "recipes": [
      "superior_stonecutter:biomesoplenty/wood/maple/maple_stick_3"
    ]
  },
  "fabric:load_conditions": [
    {
      "values": [
        "biomesoplenty"
      ],
      "condition": "fabric:all_mods_loaded"
    }
  ]
}
